Workbook

Sheet Read me
A1: Nigeria 2026 payroll calculation review
A2: Status | B2: Engineering reference cases — NOT accountant-approved
A3: Scope | B3: Recurring monthly earnings plus reviewed period adjustments; Nigeria 2026 only.
A4: Instructions | B4: Change blue inputs on Calculation. Review assumptions and evidence. Reconcile every case with your accountant.
A5: Rounding | B5: Positive half-up to two decimal naira places (integer kobo). Monthly PAYE rounds the unrounded annual band tax divided by 12.
A6: Pension | B6: 8% employee / 10% employer on basic + housing + transport; confirm contractual pensionable emoluments and applicability.
A7: NHF | B7: Opt-in/applicability per employee. Default 2.5% basic. Official guidance differs on basis; confirm before approving.
A8: PAYE reliefs | B8: Pension, NHF, NHIS, declared rent relief (20%, capped 500,000), and approved other eligible annual reliefs.
A9: Minimum wage | B9: Monthly gross at or below 70,000 treated as PAYE-exempt; confirm the employee’s legal eligibility.
A10: Employer levies | B10: ECS default 1% gross. ITF is disabled until applicability is confirmed; normally 1% annual payroll for eligible employers.
A11: Period adjustments | B11: Calendar-day starters, bonuses and one-off deductions. Period review sheet uses supplied reviewed PAYE, not a cumulative tax estimate. NHIS and recurring after-tax deductions are not prorated.
A12: Not supported | B12: Automatic cumulative/YTD PAYE, arrears, leaver calculations, unpaid absence, foreign currency or nonresident cases.
A13: Sources | B13: See Sources sheet. Tax legislation and accountant signoff control over this workbook.
... A16: Launch target | B16: Company signup → first approved payroll <=24 hours. This is measured in app analytics; it is not a guarantee.

Sheet Settings
A1: Parameter | B1: Value
A2: Employee pension | B2: 0.08
A3: Employer pension | B3: 0.1
A4: NHF rate | B4: 0.025
A5: NHF basis | B5: basic
A6: Rent relief rate | B6: 0.2
A7: Rent relief maximum | B7: 500000
A8: Minimum wage | B8: 70000
A9: Employer ECS rate | B9: 0.01
A10: Employer ITF rate | B10: 0
A11: Pension basis | B11: bht

Sheet Calculation
A1: Case | B1: Basic | C1: Housing | D1: Transport | E1: Other earnings | F1: Annual rent | G1: NHIS monthly | H1: Other deductions | I1: Annual other reliefs | J1: Pension? | K1: NHF? | L1: Gross | M1: Pension | N1: Employer pension | O1: NHF | P1: Rent relief | Q1: Annual taxable | R1: Raw annual band tax | S1: Monthly PAYE | T1: Total deductions | U1: Net pay | V1: Employer ECS | W1: Employer ITF | X1: Expected PAYE | Y1: Expected net | Z1: PAYE delta | AA1: Net delta
A2: Minimum wage | B2: 70000 | C2: 0 | D2: 0 | E2: 0 | F2: 0 | G2: 0 | H2: 0 | I2: 0 | J2: No | K2: No | L2: =SUM(B2:E2) -> 70000 | M2: =IF(J2="Yes",ROUND(IF(Settings!$B$11="gross",L2,SUM(B2:D2))*Settings!$B$2,2),0) -> 0 | N2: =IF(J2="Yes",ROUND(IF(Settings!$B$11="gross",L2,SUM(B2:D2))*Settings!$B$3,2),0) -> 0 | O2: =IF(K2="Yes",ROUND(IF(Settings!$B$5="gross",L2,B2)*Settings!$B$4,2),0) -> 0 | P2: =MIN(ROUND(F2*Settings!$B$6,2),Settings!$B$7) -> 0 | Q2: =MAX(0,(L2-M2-O2-G2)*12-P2-I2) -> 840000 | R2: =MIN(MAX(Q2-800000,0),2200000)*0.15+MIN(MAX(Q2-3000000,0),9000000)*0.18+MIN(MAX(Q2-12000000,0),13000000)*0.21+MIN(MAX(Q2-25000000,0),25000000)*0.23+MAX(Q2-50000000,0)*0.25 -> 6000 | S2: =IF(L2<=Settings!$B$8,0,ROUND(R2/12,2)) -> 0 | T2: =SUM(M2,O2,G2,H2,S2) -> 0 | U2: =L2-T2 -> 70000 | V2: =ROUND(L2*Settings!$B$9,2) -> 700 | W2: =ROUND(L2*Settings!$B$10,2) -> 0 | X2: 0 | Y2: 70000 | Z2: =S2-X2 -> 0 | AA2: =U2-Y2 -> 0
A3: Just above minimum wage | B3: 70000.01 | C3: 0 | D3: 0 | E3: 0 | F3: 0 | G3: 0 | H3: 0 | I3: 0 | J3: No | K3: No | L3: =SUM(B3:E3) -> 70000.01 | M3: =IF(J3="Yes",ROUND(IF(Settings!$B$11="gross",L3,SUM(B3:D3))*Settings!$B$2,2),0) -> 0 | N3: =IF(J3="Yes",ROUND(IF(Settings!$B$11="gross",L3,SUM(B3:D3))*Settings!$B$3,2),0) -> 0 | O3: =IF(K3="Yes",ROUND(IF(Settings!$B$5="gross",L3,B3)*Settings!$B$4,2),0) -> 0 | P3: =MIN(ROUND(F3*Settings!$B$6,2),Settings!$B$7) -> 0 | Q3: =MAX(0,(L3-M3-O3-G3)*12-P3-I3) -> 840000.12 | R3: =MIN(MAX(Q3-800000,0),2200000)*0.15+MIN(MAX(Q3-3000000,0),9000000)*0.18+MIN(MAX(Q3-12000000,0),13000000)*0.21+MIN(MAX(Q3-25000000,0),25000000)*0.23+MAX(Q3-50000000,0)*0.25 -> 6000.018 | S3: =IF(L3<=Settings!$B$8,0,ROUND(R3/12,2)) -> 500 | T3: =SUM(M3,O3,G3,H3,S3) -> 500 | U3: =L3-T3 -> 69500.01 | V3: =ROUND(L3*Settings!$B$9,2) -> 700 | W3: =ROUND(L3*Settings!$B$10,2) -> 0 | X3: 500 | Y3: 69500.01 | Z3: =S3-X3 -> 0 | AA3: =U3-Y3 -> 0
A4: Basic salary with pension | B4: 200000 | C4: 0 | D4: 0 | E4: 0 | F4: 0 | G4: 0 | H4: 0 | I4: 0 | J4: Yes | K4: No | L4: =SUM(B4:E4) -> 200000 | M4: =IF(J4="Yes",ROUND(IF(Settings!$B$11="gross",L4,SUM(B4:D4))*Settings!$B$2,2),0) -> 16000 | N4: =IF(J4="Yes",ROUND(IF(Settings!$B$11="gross",L4,SUM(B4:D4))*Settings!$B$3,2),0) -> 20000 | O4: =IF(K4="Yes",ROUND(IF(Settings!$B$5="gross",L4,B4)*Settings!$B$4,2),0) -> 0 | P4: =MIN(ROUND(F4*Settings!$B$6,2),Settings!$B$7) -> 0 | Q4: =MAX(0,(L4-M4-O4-G4)*12-P4-I4) -> 2208000 | R4: =MIN(MAX(Q4-800000,0),2200000)*0.15+MIN(MAX(Q4-3000000,0),9000000)*0.18+MIN(MAX(Q4-12000000,0),13000000)*0.21+MIN(MAX(Q4-25000000,0),25000000)*0.23+MAX(Q4-50000000,0)*0.25 -> 211200 | S4: =IF(L4<=Settings!$B$8,0,ROUND(R4/12,2)) -> 17600 | T4: =SUM(M4,O4,G4,H4,S4) -> 33600 | U4: =L4-T4 -> 166400 | V4: =ROUND(L4*Settings!$B$9,2) -> 2000 | W4: =ROUND(L4*Settings!$B$10,2) -> 0 | X4: 17600 | Y4: 166400 | Z4: =S4-X4 -> 0 | AA4: =U4-Y4 -> 0
A5: PAYE band: annual 3m | B5: 250000 | C5: 0 | D5: 0 | E5: 0 | F5: 0 | G5: 0 | H5: 0 | I5: 0 | J5: No | K5: No | L5: =SUM(B5:E5) -> 250000 | M5: =IF(J5="Yes",ROUND(IF(Settings!$B$11="gross",L5,SUM(B5:D5))*Settings!$B$2,2),0) -> 0 | N5: =IF(J5="Yes",ROUND(IF(Settings!$B$11="gross",L5,SUM(B5:D5))*Settings!$B$3,2),0) -> 0 | O5: =IF(K5="Yes",ROUND(IF(Settings!$B$5="gross",L5,B5)*Settings!$B$4,2),0) -> 0 | P5: =MIN(ROUND(F5*Settings!$B$6,2),Settings!$B$7) -> 0 | Q5: =MAX(0,(L5-M5-O5-G5)*12-P5-I5) -> 3000000 | R5: =MIN(MAX(Q5-800000,0),2200000)*0.15+MIN(MAX(Q5-3000000,0),9000000)*0.18+MIN(MAX(Q5-12000000,0),13000000)*0.21+MIN(MAX(Q5-25000000,0),25000000)*0.23+MAX(Q5-50000000,0)*0.25 -> 330000 | S5: =IF(L5<=Settings!$B$8,0,ROUND(R5/12,2)) -> 27500 | T5: =SUM(M5,O5,G5,H5,S5) -> 27500 | U5: =L5-T5 -> 222500 | V5: =ROUND(L5*Settings!$B$9,2) -> 2500 | W5: =ROUND(L5*Settings!$B$10,2) -> 0 | X5: 27500 | Y5: 222500 | Z5: =S5-X5 -> 0 | AA5: =U5-Y5 -> 0
A6: PAYE band: annual 12m | B6: 1000000 | C6: 0 | D6: 0 | E6: 0 | F6: 0 | G6: 0 | H6: 0 | I6: 0 | J6: No | K6: No | L6: =SUM(B6:E6) -> 1000000 | M6: =IF(J6="Yes",ROUND(IF(Settings!$B$11="gross",L6,SUM(B6:D6))*Settings!$B$2,2),0) -> 0 | N6: =IF(J6="Yes",ROUND(IF(Settings!$B$11="gross",L6,SUM(B6:D6))*Settings!$B$3,2),0) -> 0 | O6: =IF(K6="Yes",ROUND(IF(Settings!$B$5="gross",L6,B6)*Settings!$B$4,2),0) -> 0 | P6: =MIN(ROUND(F6*Settings!$B$6,2),Settings!$B$7) -> 0 | Q6: =MAX(0,(L6-M6-O6-G6)*12-P6-I6) -> 12000000 | R6: =MIN(MAX(Q6-800000,0),2200000)*0.15+MIN(MAX(Q6-3000000,0),9000000)*0.18+MIN(MAX(Q6-12000000,0),13000000)*0.21+MIN(MAX(Q6-25000000,0),25000000)*0.23+MAX(Q6-50000000,0)*0.25 -> 1950000 | S6: =IF(L6<=Settings!$B$8,0,ROUND(R6/12,2)) -> 162500 | T6: =SUM(M6,O6,G6,H6,S6) -> 162500 | U6: =L6-T6 -> 837500 | V6: =ROUND(L6*Settings!$B$9,2) -> 10000 | W6: =ROUND(L6*Settings!$B$10,2) -> 0 | X6: 162500 | Y6: 837500 | Z6: =S6-X6 -> 0 | AA6: =U6-Y6 -> 0
A7: PAYE band: around annual 25m | B7: 2083333.3 | C7: 0 | D7: 0 | E7: 0 | F7: 0 | G7: 0 | H7: 0 | I7: 0 | J7: No | K7: No | L7: =SUM(B7:E7) -> 2083333.3 | M7: =IF(J7="Yes",ROUND(IF(Settings!$B$11="gross",L7,SUM(B7:D7))*Settings!$B$2,2),0) -> 0 | N7: =IF(J7="Yes",ROUND(IF(Settings!$B$11="gross",L7,SUM(B7:D7))*Settings!$B$3,2),0) -> 0 | O7: =IF(K7="Yes",ROUND(IF(Settings!$B$5="gross",L7,B7)*Settings!$B$4,2),0) -> 0 | P7: =MIN(ROUND(F7*Settings!$B$6,2),Settings!$B$7) -> 0 | Q7: =MAX(0,(L7-M7-O7-G7)*12-P7-I7) -> 25000000 | R7: =MIN(MAX(Q7-800000,0),2200000)*0.15+MIN(MAX(Q7-3000000,0),9000000)*0.18+MIN(MAX(Q7-12000000,0),13000000)*0.21+MIN(MAX(Q7-25000000,0),25000000)*0.23+MAX(Q7-50000000,0)*0.25 -> 4680000 | S7: =IF(L7<=Settings!$B$8,0,ROUND(R7/12,2)) -> 390000 | T7: =SUM(M7,O7,G7,H7,S7) -> 390000 | U7: =L7-T7 -> 1693333.3 | V7: =ROUND(L7*Settings!$B$9,2) -> 20833.33 | W7: =ROUND(L7*Settings!$B$10,2) -> 0 | X7: 390000 | Y7: 1693333.3 | Z7: =S7-X7 -> 0 | AA7: =U7-Y7 -> 0
A8: PAYE band: around annual 50m | B8: 4166666.7 | C8: 0 | D8: 0 | E8: 0 | F8: 0 | G8: 0 | H8: 0 | I8: 0 | J8: No | K8: No | L8: =SUM(B8:E8) -> 4166666.7 | M8: =IF(J8="Yes",ROUND(IF(Settings!$B$11="gross",L8,SUM(B8:D8))*Settings!$B$2,2),0) -> 0 | N8: =IF(J8="Yes",ROUND(IF(Settings!$B$11="gross",L8,SUM(B8:D8))*Settings!$B$3,2),0) -> 0 | O8: =IF(K8="Yes",ROUND(IF(Settings!$B$5="gross",L8,B8)*Settings!$B$4,2),0) -> 0 | P8: =MIN(ROUND(F8*Settings!$B$6,2),Settings!$B$7) -> 0 | Q8: =MAX(0,(L8-M8-O8-G8)*12-P8-I8) -> 50000000 | R8: =MIN(MAX(Q8-800000,0),2200000)*0.15+MIN(MAX(Q8-3000000,0),9000000)*0.18+MIN(MAX(Q8-12000000,0),13000000)*0.21+MIN(MAX(Q8-25000000,0),25000000)*0.23+MAX(Q8-50000000,0)*0.25 -> 10430000 | S8: =IF(L8<=Settings!$B$8,0,ROUND(R8/12,2)) -> 869166.67 | T8: =SUM(M8,O8,G8,H8,S8) -> 869166.67 | U8: =L8-T8 -> 3297500 | V8: =ROUND(L8*Settings!$B$9,2) -> 41666.67 | W8: =ROUND(L8*Settings!$B$10,2) -> 0 | X8: 869166.67 | Y8: 3297500 | Z8: =S8-X8 -> 0 | AA8: =U8-Y8 -> 0
A9: PAYE top band: annual 60m | B9: 5000000 | C9: 0 | D9: 0 | E9: 0 | F9: 0 | G9: 0 | H9: 0 | I9: 0 | J9: No | K9: No | L9: =SUM(B9:E9) -> 5000000 | M9: =IF(J9="Yes",ROUND(IF(Settings!$B$11="gross",L9,SUM(B9:D9))*Settings!$B$2,2),0) -> 0 | N9: =IF(J9="Yes",ROUND(IF(Settings!$B$11="gross",L9,SUM(B9:D9))*Settings!$B$3,2),0) -> 0 | O9: =IF(K9="Yes",ROUND(IF(Settings!$B$5="gross",L9,B9)*Settings!$B$4,2),0) -> 0 | P9: =MIN(ROUND(F9*Settings!$B$6,2),Settings!$B$7) -> 0 | Q9: =MAX(0,(L9-M9-O9-G9)*12-P9-I9) -> 60000000 | R9: =MIN(MAX(Q9-800000,0),2200000)*0.15+MIN(MAX(Q9-3000000,0),9000000)*0.18+MIN(MAX(Q9-12000000,0),13000000)*0.21+MIN(MAX(Q9-25000000,0),25000000)*0.23+MAX(Q9-50000000,0)*0.25 -> 12930000 | S9: =IF(L9<=Settings!$B$8,0,ROUND(R9/12,2)) -> 1077500 | T9: =SUM(M9,O9,G9,H9,S9) -> 1077500 | U9: =L9-T9 -> 3922500 | V9: =ROUND(L9*Settings!$B$9,2) -> 50000 | W9: =ROUND(L9*Settings!$B$10,2) -> 0 | X9: 1077500 | Y9: 3922500 | Z9: =S9-X9 -> 0 | AA9: =U9-Y9 -> 0
A10: Pension NHF and rent relief | B10: 200000 | C10: 100000 | D10: 50000 | E10: 0 | F10: 1200000 | G10: 0 | H10: 0 | I10: 0 | J10: Yes | K10: Yes | L10: =SUM(B10:E10) -> 350000 | M10: =IF(J10="Yes",ROUND(IF(Settings!$B$11="gross",L10,SUM(B10:D10))*Settings!$B$2,2),0) -> 28000 | N10: =IF(J10="Yes",ROUND(IF(Settings!$B$11="gross",L10,SUM(B10:D10))*Settings!$B$3,2),0) -> 35000 | O10: =IF(K10="Yes",ROUND(IF(Settings!$B$5="gross",L10,B10)*Settings!$B$4,2),0) -> 5000 | P10: =MIN(ROUND(F10*Settings!$B$6,2),Settings!$B$7) -> 240000 | Q10: =MAX(0,(L10-M10-O10-G10)*12-P10-I10) -> 3564000 | R10: =MIN(MAX(Q10-800000,0),2200000)*0.15+MIN(MAX(Q10-3000000,0),9000000)*0.18+MIN(MAX(Q10-12000000,0),13000000)*0.21+MIN(MAX(Q10-25000000,0),25000000)*0.23+MAX(Q10-50000000,0)*0.25 -> 431520 | S10: =IF(L10<=Settings!$B$8,0,ROUND(R10/12,2)) -> 35960 | T10: =SUM(M10,O10,G10,H10,S10) -> 68960 | U10: =L10-T10 -> 281040 | V10: =ROUND(L10*Settings!$B$9,2) -> 3500 | W10: =ROUND(L10*Settings!$B$10,2) -> 0 | X10: 35960 | Y10: 281040 | Z10: =S10-X10 -> 0 | AA10: =U10-Y10 -> 0
A11: Rent relief cap | B11: 350000 | C11: 0 | D11: 0 | E11: 0 | F11: 4000000 | G11: 0 | H11: 0 | I11: 0 | J11: Yes | K11: No | L11: =SUM(B11:E11) -> 350000 | M11: =IF(J11="Yes",ROUND(IF(Settings!$B$11="gross",L11,SUM(B11:D11))*Settings!$B$2,2),0) -> 28000 | N11: =IF(J11="Yes",ROUND(IF(Settings!$B$11="gross",L11,SUM(B11:D11))*Settings!$B$3,2),0) -> 35000 | O11: =IF(K11="Yes",ROUND(IF(Settings!$B$5="gross",L11,B11)*Settings!$B$4,2),0) -> 0 | P11: =MIN(ROUND(F11*Settings!$B$6,2),Settings!$B$7) -> 500000 | Q11: =MAX(0,(L11-M11-O11-G11)*12-P11-I11) -> 3364000 | R11: =MIN(MAX(Q11-800000,0),2200000)*0.15+MIN(MAX(Q11-3000000,0),9000000)*0.18+MIN(MAX(Q11-12000000,0),13000000)*0.21+MIN(MAX(Q11-25000000,0),25000000)*0.23+MAX(Q11-50000000,0)*0.25 -> 395520 | S11: =IF(L11<=Settings!$B$8,0,ROUND(R11/12,2)) -> 32960 | T11: =SUM(M11,O11,G11,H11,S11) -> 60960 | U11: =L11-T11 -> 289040 | V11: =ROUND(L11*Settings!$B$9,2) -> 3500 | W11: =ROUND(L11*Settings!$B$10,2) -> 0 | X11: 32960 | Y11: 289040 | Z11: =S11-X11 -> 0 | AA11: =U11-Y11 -> 0
A12: NHIS and other deductions | B12: 250000 | C12: 0 | D12: 0 | E12: 0 | F12: 0 | G12: 10000 | H12: 5000 | I12: 0 | J12: Yes | K12: No | L12: =SUM(B12:E12) -> 250000 | M12: =IF(J12="Yes",ROUND(IF(Settings!$B$11="gross",L12,SUM(B12:D12))*Settings!$B$2,2),0) -> 20000 | N12: =IF(J12="Yes",ROUND(IF(Settings!$B$11="gross",L12,SUM(B12:D12))*Settings!$B$3,2),0) -> 25000 | O12: =IF(K12="Yes",ROUND(IF(Settings!$B$5="gross",L12,B12)*Settings!$B$4,2),0) -> 0 | P12: =MIN(ROUND(F12*Settings!$B$6,2),Settings!$B$7) -> 0 | Q12: =MAX(0,(L12-M12-O12-G12)*12-P12-I12) -> 2640000 | R12: =MIN(MAX(Q12-800000,0),2200000)*0.15+MIN(MAX(Q12-3000000,0),9000000)*0.18+MIN(MAX(Q12-12000000,0),13000000)*0.21+MIN(MAX(Q12-25000000,0),25000000)*0.23+MAX(Q12-50000000,0)*0.25 -> 276000 | S12: =IF(L12<=Settings!$B$8,0,ROUND(R12/12,2)) -> 23000 | T12: =SUM(M12,O12,G12,H12,S12) -> 58000 | U12: =L12-T12 -> 192000 | V12: =ROUND(L12*Settings!$B$9,2) -> 2500 | W12: =ROUND(L12*Settings!$B$10,2) -> 0 | X12: 23000 | Y12: 192000 | Z12: =S12-X12 -> 0 | AA12: =U12-Y12 -> 0
A13: Other recurring earnings | B13: 200000 | C13: 50000 | D13: 25000 | E13: 75000 | F13: 0 | G13: 0 | H13: 0 | I13: 0 | J13: Yes | K13: Yes | L13: =SUM(B13:E13) -> 350000 | M13: =IF(J13="Yes",ROUND(IF(Settings!$B$11="gross",L13,SUM(B13:D13))*Settings!$B$2,2),0) -> 22000 | N13: =IF(J13="Yes",ROUND(IF(Settings!$B$11="gross",L13,SUM(B13:D13))*Settings!$B$3,2),0) -> 27500 | O13: =IF(K13="Yes",ROUND(IF(Settings!$B$5="gross",L13,B13)*Settings!$B$4,2),0) -> 5000 | P13: =MIN(ROUND(F13*Settings!$B$6,2),Settings!$B$7) -> 0 | Q13: =MAX(0,(L13-M13-O13-G13)*12-P13-I13) -> 3876000 | R13: =MIN(MAX(Q13-800000,0),2200000)*0.15+MIN(MAX(Q13-3000000,0),9000000)*0.18+MIN(MAX(Q13-12000000,0),13000000)*0.21+MIN(MAX(Q13-25000000,0),25000000)*0.23+MAX(Q13-50000000,0)*0.25 -> 487680 | S13: =IF(L13<=Settings!$B$8,0,ROUND(R13/12,2)) -> 40640 | T13: =SUM(M13,O13,G13,H13,S13) -> 67640 | U13: =L13-T13 -> 282360 | V13: =ROUND(L13*Settings!$B$9,2) -> 3500 | W13: =ROUND(L13*Settings!$B$10,2) -> 0 | X13: 40640 | Y13: 282360 | Z13: =S13-X13 -> 0 | AA13: =U13-Y13 -> 0
... A16: Taxable zero after reliefs | B16: 100000 | C16: 0 | D16: 0 | E16: 0 | F16: 0 | G16: 0 | H16: 0 | I16: 1200000 | J16: No | K16: No | L16: =SUM(B16:E16) -> 100000 | M16: =IF(J16="Yes",ROUND(IF(Settings!$B$11="gross",L16,SUM(B16:D16))*Settings!$B$2,2),0) -> 0 | N16: =IF(J16="Yes",ROUND(IF(Settings!$B$11="gross",L16,SUM(B16:D16))*Settings!$B$3,2),0) -> 0 | O16: =IF(K16="Yes",ROUND(IF(Settings!$B$5="gross",L16,B16)*Settings!$B$4,2),0) -> 0 | P16: =MIN(ROUND(F16*Settings!$B$6,2),Settings!$B$7) -> 0 | Q16: =MAX(0,(L16-M16-O16-G16)*12-P16-I16) -> 0 | R16: =MIN(MAX(Q16-800000,0),2200000)*0.15+MIN(MAX(Q16-3000000,0),9000000)*0.18+MIN(MAX(Q16-12000000,0),13000000)*0.21+MIN(MAX(Q16-25000000,0),25000000)*0.23+MAX(Q16-50000000,0)*0.25 -> 0 | S16: =IF(L16<=Settings!$B$8,0,ROUND(R16/12,2)) -> 0 | T16: =SUM(M16,O16,G16,H16,S16) -> 0 | U16: =L16-T16 -> 100000 | V16: =ROUND(L16*Settings!$B$9,2) -> 1000 | W16: =ROUND(L16*Settings!$B$10,2) -> 0 | X16: 0 | Y16: 100000 | Z16: =S16-X16 -> 0 | AA16: =U16-Y16 -> 0

Sheet Reference
A1: Case | B1: gross | C1: paye | D1: pension | E1: employer_pension | F1: nhf | G1: nhis | H1: total_deductions | I1: net | J1: employer_ecs | K1: employer_itf
A2: Minimum wage | B2: 70000 | C2: 0 | D2: 0 | E2: 0 | F2: 0 | G2: 0 | H2: 0 | I2: 70000 | J2: 700 | K2: 0
A3: Just above minimum wage | B3: 70000.01 | C3: 500 | D3: 0 | E3: 0 | F3: 0 | G3: 0 | H3: 500 | I3: 69500.01 | J3: 700 | K3: 0
A4: Basic salary with pension | B4: 200000 | C4: 17600 | D4: 16000 | E4: 20000 | F4: 0 | G4: 0 | H4: 33600 | I4: 166400 | J4: 2000 | K4: 0
A5: PAYE band: annual 3m | B5: 250000 | C5: 27500 | D5: 0 | E5: 0 | F5: 0 | G5: 0 | H5: 27500 | I5: 222500 | J5: 2500 | K5: 0
A6: PAYE band: annual 12m | B6: 1000000 | C6: 162500 | D6: 0 | E6: 0 | F6: 0 | G6: 0 | H6: 162500 | I6: 837500 | J6: 10000 | K6: 0
A7: PAYE band: around annual 25m | B7: 2083333.3 | C7: 390000 | D7: 0 | E7: 0 | F7: 0 | G7: 0 | H7: 390000 | I7: 1693333.3 | J7: 20833.33 | K7: 0
A8: PAYE band: around annual 50m | B8: 4166666.7 | C8: 869166.67 | D8: 0 | E8: 0 | F8: 0 | G8: 0 | H8: 869166.67 | I8: 3297500 | J8: 41666.67 | K8: 0
A9: PAYE top band: annual 60m | B9: 5000000 | C9: 1077500 | D9: 0 | E9: 0 | F9: 0 | G9: 0 | H9: 1077500 | I9: 3922500 | J9: 50000 | K9: 0
A10: Pension NHF and rent relief | B10: 350000 | C10: 35960 | D10: 28000 | E10: 35000 | F10: 5000 | G10: 0 | H10: 68960 | I10: 281040 | J10: 3500 | K10: 0
A11: Rent relief cap | B11: 350000 | C11: 32960 | D11: 28000 | E11: 35000 | F11: 0 | G11: 0 | H11: 60960 | I11: 289040 | J11: 3500 | K11: 0
A12: NHIS and other deductions | B12: 250000 | C12: 23000 | D12: 20000 | E12: 25000 | F12: 0 | G12: 10000 | H12: 58000 | I12: 192000 | J12: 2500 | K12: 0
A13: Other recurring earnings | B13: 350000 | C13: 40640 | D13: 22000 | E13: 27500 | F13: 5000 | G13: 0 | H13: 67640 | I13: 282360 | J13: 3500 | K13: 0
... A16: Taxable zero after reliefs | B16: 100000 | C16: 0 | D16: 0 | E16: 0 | F16: 0 | G16: 0 | H16: 0 | I16: 100000 | J16: 1000 | K16: 0

Sheet Sources
A1: Source | B1: URL | C1: Use / review note
A2: Nigeria Tax Act 2025 | B2: https://www.nrs.gov.ng/uploads/NIGERIA_TAX_ACT_2025_ef6bb812a5.pdf | C2: 2026 bands and eligible deductions; legislation controls.
A3: NRS legislation index | B3: https://www.nrs.gov.ng/tax-laws/page | C3: Official law index.
A4: Plateau State IRS 2026 calculator | B4: https://www.psirs.gov.ng/tax-calculator | C4: Effective date and rent-relief guidance.
A5: PenCom 2023 FAQ | B5: https://www.pencom.gov.ng/wp-content/uploads/2023/09/FREQUENTLY-ASKED-QUESTIONS-2023.pdf | C5: Monthly emoluments; 8% employee / 10% employer minimum.
A6: FMBN current FAQ | B6: https://fmbn.gov.ng/products/nhf-scheme/faqs | C6: Current wording refers to gross income. Confirm NHF base.
A7: FMBN service charter | B7: https://www.fmbn.gov.ng/documents/FMBN_SERVICOM_CHARTER.pdf | C7: Earlier wording refers to basic salary; confirm applicable guidance.
A8: NSITF services | B8: https://nsitf.gov.ng/services | C8: Employer ECS 1% total monthly payroll.
A9: ITF | B9: https://www.itf.gov.ng/ | C9: Eligibility and 1% annual payroll contribution.

Sheet Period review
A1: Case | B1: Calendar days | C1: Paid days | D1: Basic monthly | E1: Housing monthly | F1: Transport monthly | G1: Other monthly | H1: Bonus | I1: Pensionable bonus BHT | J1: Reviewed PAYE INPUT | K1: NHIS fixed | L1: Recurring deductions fixed | M1: One-off deduction | N1: Pension? | O1: NHF? | P1: Gross | Q1: Employee pension | R1: Employer pension | S1: NHF | T1: Total deductions | U1: Net | V1: Employer ECS | W1: Employer ITF | X1: Expected net | Y1: Net delta
A2: October starter and bonus | B2: 31 | C2: 16 | D2: 310000 | E2: 0 | F2: 0 | G2: 0 | H2: 50000 | I2: 0 | J2: 12000 | K2: 0 | L2: 0 | M2: 5000 | N2: No | O2: No | P2: =ROUND(D2*C2/B2,2)+ROUND(E2*C2/B2,2)+ROUND(F2*C2/B2,2)+ROUND(G2*C2/B2,2)+H2 -> 210000 | Q2: =IF(N2="Yes",ROUND(IF(Settings!$B$11="gross",P2,ROUND(D2*C2/B2,2)+ROUND(E2*C2/B2,2)+ROUND(F2*C2/B2,2)+I2)*Settings!$B$2,2),0) -> 0 | R2: =IF(N2="Yes",ROUND(IF(Settings!$B$11="gross",P2,ROUND(D2*C2/B2,2)+ROUND(E2*C2/B2,2)+ROUND(F2*C2/B2,2)+I2)*Settings!$B$3,2),0) -> 0 | S2: =IF(O2="Yes",ROUND(IF(Settings!$B$5="gross",P2,ROUND(D2*C2/B2,2))*Settings!$B$4,2),0) -> 0 | T2: =SUM(J2:M2)+Q2+S2 -> 17000 | U2: =P2-T2 -> 193000 | V2: =ROUND(P2*Settings!$B$9,2) -> 2100 | W2: =ROUND(P2*Settings!$B$10,2) -> 0 | X2: 193000 | Y2: =U2-X2 -> 0
A3: Starter pensionable bonus NHF | B3: 31 | C3: 16 | D3: 310000 | E3: 0 | F3: 0 | G3: 0 | H3: 50000 | I3: 20000 | J3: 8000 | K3: 0 | L3: 0 | M3: 5000 | N3: Yes | O3: Yes | P3: =ROUND(D3*C3/B3,2)+ROUND(E3*C3/B3,2)+ROUND(F3*C3/B3,2)+ROUND(G3*C3/B3,2)+H3 -> 210000 | Q3: =IF(N3="Yes",ROUND(IF(Settings!$B$11="gross",P3,ROUND(D3*C3/B3,2)+ROUND(E3*C3/B3,2)+ROUND(F3*C3/B3,2)+I3)*Settings!$B$2,2),0) -> 14400 | R3: =IF(N3="Yes",ROUND(IF(Settings!$B$11="gross",P3,ROUND(D3*C3/B3,2)+ROUND(E3*C3/B3,2)+ROUND(F3*C3/B3,2)+I3)*Settings!$B$3,2),0) -> 18000 | S3: =IF(O3="Yes",ROUND(IF(Settings!$B$5="gross",P3,ROUND(D3*C3/B3,2))*Settings!$B$4,2),0) -> 4000 | T3: =SUM(J3:M3)+Q3+S3 -> 31400 | U3: =P3-T3 -> 178600 | V3: =ROUND(P3*Settings!$B$9,2) -> 2100 | W3: =ROUND(P3*Settings!$B$10,2) -> 0 | X3: 178600 | Y3: =U3-X3 -> 0
A4: February half month | B4: 28 | C4: 14 | D4: 200000 | E4: 0 | F4: 0 | G4: 0 | H4: 0 | I4: 0 | J4: 3000 | K4: 0 | L4: 0 | M4: 0 | N4: Yes | O4: No | P4: =ROUND(D4*C4/B4,2)+ROUND(E4*C4/B4,2)+ROUND(F4*C4/B4,2)+ROUND(G4*C4/B4,2)+H4 -> 100000 | Q4: =IF(N4="Yes",ROUND(IF(Settings!$B$11="gross",P4,ROUND(D4*C4/B4,2)+ROUND(E4*C4/B4,2)+ROUND(F4*C4/B4,2)+I4)*Settings!$B$2,2),0) -> 8000 | R4: =IF(N4="Yes",ROUND(IF(Settings!$B$11="gross",P4,ROUND(D4*C4/B4,2)+ROUND(E4*C4/B4,2)+ROUND(F4*C4/B4,2)+I4)*Settings!$B$3,2),0) -> 10000 | S4: =IF(O4="Yes",ROUND(IF(Settings!$B$5="gross",P4,ROUND(D4*C4/B4,2))*Settings!$B$4,2),0) -> 0 | T4: =SUM(J4:M4)+Q4+S4 -> 11000 | U4: =P4-T4 -> 89000 | V4: =ROUND(P4*Settings!$B$9,2) -> 1000 | W4: =ROUND(P4*Settings!$B$10,2) -> 0 | X4: 89000 | Y4: =U4-X4 -> 0
A5: Full month pensionable bonus | B5: 31 | C5: 31 | D5: 200000 | E5: 0 | F5: 0 | G5: 0 | H5: 100000 | I5: 100000 | J5: 25000 | K5: 0 | L5: 0 | M5: 0 | N5: Yes | O5: No | P5: =ROUND(D5*C5/B5,2)+ROUND(E5*C5/B5,2)+ROUND(F5*C5/B5,2)+ROUND(G5*C5/B5,2)+H5 -> 300000 | Q5: =IF(N5="Yes",ROUND(IF(Settings!$B$11="gross",P5,ROUND(D5*C5/B5,2)+ROUND(E5*C5/B5,2)+ROUND(F5*C5/B5,2)+I5)*Settings!$B$2,2),0) -> 24000 | R5: =IF(N5="Yes",ROUND(IF(Settings!$B$11="gross",P5,ROUND(D5*C5/B5,2)+ROUND(E5*C5/B5,2)+ROUND(F5*C5/B5,2)+I5)*Settings!$B$3,2),0) -> 30000 | S5: =IF(O5="Yes",ROUND(IF(Settings!$B$5="gross",P5,ROUND(D5*C5/B5,2))*Settings!$B$4,2),0) -> 0 | T5: =SUM(J5:M5)+Q5+S5 -> 49000 | U5: =P5-T5 -> 251000 | V5: =ROUND(P5*Settings!$B$9,2) -> 3000 | W5: =ROUND(P5*Settings!$B$10,2) -> 0 | X5: 251000 | Y5: =U5-X5 -> 0
A6: Partial minimum wage explicit zero | B6: 31 | C6: 1 | D6: 70000 | E6: 0 | F6: 0 | G6: 0 | H6: 0 | I6: 0 | J6: 0 | K6: 0 | L6: 0 | M6: 0 | N6: No | O6: No | P6: =ROUND(D6*C6/B6,2)+ROUND(E6*C6/B6,2)+ROUND(F6*C6/B6,2)+ROUND(G6*C6/B6,2)+H6 -> 2258.06 | Q6: =IF(N6="Yes",ROUND(IF(Settings!$B$11="gross",P6,ROUND(D6*C6/B6,2)+ROUND(E6*C6/B6,2)+ROUND(F6*C6/B6,2)+I6)*Settings!$B$2,2),0) -> 0 | R6: =IF(N6="Yes",ROUND(IF(Settings!$B$11="gross",P6,ROUND(D6*C6/B6,2)+ROUND(E6*C6/B6,2)+ROUND(F6*C6/B6,2)+I6)*Settings!$B$3,2),0) -> 0 | S6: =IF(O6="Yes",ROUND(IF(Settings!$B$5="gross",P6,ROUND(D6*C6/B6,2))*Settings!$B$4,2),0) -> 0 | T6: =SUM(J6:M6)+Q6+S6 -> 0 | U6: =P6-T6 -> 2258.06 | V6: =ROUND(P6*Settings!$B$9,2) -> 22.58 | W6: =ROUND(P6*Settings!$B$10,2) -> 0 | X6: 2258.06 | Y6: =U6-X6 -> 0
A7: Component rounding | B7: 31 | C7: 15 | D7: 123456.78 | E7: 23456.79 | F7: 3456.78 | G7: 111.11 | H7: 500.01 | I7: 100.01 | J7: 1500.01 | K7: 123.45 | L7: 11.11 | M7: 2.22 | N7: Yes | O7: Yes | P7: =ROUND(D7*C7/B7,2)+ROUND(E7*C7/B7,2)+ROUND(F7*C7/B7,2)+ROUND(G7*C7/B7,2)+H7 -> 73313.62 | Q7: =IF(N7="Yes",ROUND(IF(Settings!$B$11="gross",P7,ROUND(D7*C7/B7,2)+ROUND(E7*C7/B7,2)+ROUND(F7*C7/B7,2)+I7)*Settings!$B$2,2),0) -> 5828.79 | R7: =IF(N7="Yes",ROUND(IF(Settings!$B$11="gross",P7,ROUND(D7*C7/B7,2)+ROUND(E7*C7/B7,2)+ROUND(F7*C7/B7,2)+I7)*Settings!$B$3,2),0) -> 7285.99 | S7: =IF(O7="Yes",ROUND(IF(Settings!$B$5="gross",P7,ROUND(D7*C7/B7,2))*Settings!$B$4,2),0) -> 1493.43 | T7: =SUM(J7:M7)+Q7+S7 -> 8959.01 | U7: =P7-T7 -> 64354.61 | V7: =ROUND(P7*Settings!$B$9,2) -> 733.14 | W7: =ROUND(P7*Settings!$B$10,2) -> 0 | X7: 64354.61 | Y7: =U7-X7 -> 0
